__init__.py
main.py
quintus.py
__tests__/__init__.py
__tests__/test_quintus.py
database/__init__.py
database/agent.py
database/engine.py
database/entity.py
database/repository.py
database/schema/__init__.py
database/schema/chat.py
database/schema/config.py
database/schema/document.py
database/schema/message.py
examples/__init__.py
examples/infer.py
examples/zendesk.py
inference/__init__.py
inference/local/__init__.py
inference/local/chat.py
inference/local/generate.py
inference/local/model.py
inference/local/stream.py
inference/openai/__init__.py
inference/openai/chat.py
inference/tasks/chat.py
inference/tasks/ner.py
inference/tasks/summarization.py
loaders/__init__.py
loaders/base.py
loaders/loaders.py
loaders/zendesk.py
templates/__init__.py
templates/prompts.py
templates/templates.py
utils/__init__.py
utils/encoder.py
utils/model_config.py
utils/processor.py
utils/text.py
var/constants.py
quintus-0.2.dist-info/LICENCE
quintus-0.2.dist-info/METADATA
quintus-0.2.dist-info/WHEEL
quintus-0.2.dist-info/top_level.txt
quintus-0.2.dist-info/RECORD
